ewoksid31/__init__.py
ewoksid31/app/__init__.py
ewoksid31/app/streamline_autocalib.py
ewoksid31/app/utils.py
ewoksid31/app/integrate/__init__.py
ewoksid31/app/integrate/__main__.py
ewoksid31/app/integrate/constants.py
ewoksid31/app/integrate/execution_groupbox.py
ewoksid31/app/integrate/hdf5_treeview.py
ewoksid31/app/integrate/hdf5_widget.py
ewoksid31/app/integrate/integrate.svg
ewoksid31/app/integrate/jobs_list_widget.py
ewoksid31/app/integrate/jobs_progressbar.py
ewoksid31/app/integrate/mainwindow.py
ewoksid31/app/integrate/output_groupbox.py
ewoksid31/app/integrate/processing_groupbox.py
ewoksid31/app/integrate/selection_filter_groupbox.py
ewoksid31/app/integrate/utils.py
ewoksid31/app/integrate/workflow_executor.py
ewoksid31/tasks/__init__.py
ewoksid31/tasks/flatfield.py
ewoksid31/tasks/tomo.py
ewoksid31/tests/__init__.py
ewoksid31/tests/conftest.py
ewoksid31/tests/test_flatfield.py
ewoksid31/tests/test_gui.py
ewoksid31/tests/test_tomo.py
ewoksid31/tests/test_workflow_executor.py
ewoksid31/tests/resources/__init__.py
ewoksid31/tests/resources/flats.mat
ewoksid31/tests/resources/flats_old.mat
ewoksid31/workflows/__init__.py
ewoksid31/workflows/demo.json
ewoksid31/workflows/integrate_with_saving.json
ewoksid31/workflows/integrate_with_saving_with_flat.json
ewoksid31/workflows/integrate_without_saving.json
ewoksid31/workflows/integrate_without_saving_with_flat.json
ewoksid31/workflows/streamline_autocalib.json
ewoksid31/workflows/streamline_with_calib.json
ewoksid31/workflows/streamline_with_calib_with_flat.json
ewoksid31/workflows/streamline_without_calib.json
ewoksid31/workflows/streamline_without_calib_with_flat.json
ewoksid31-0.8.1.dist-info/licenses/LICENSE.md
orangecontrib/ewoksid31/__init__.py
orangecontrib/ewoksid31/flatfield.py
orangecontrib/ewoksid31/icons/__init__.py
orangecontrib/ewoksid31/icons/category.png
orangecontrib/ewoksid31/icons/widget.png
ewoksid31-0.8.1.dist-info/METADATA
ewoksid31-0.8.1.dist-info/WHEEL
ewoksid31-0.8.1.dist-info/entry_points.txt
ewoksid31-0.8.1.dist-info/top_level.txt
ewoksid31-0.8.1.dist-info/RECORD
