Metadata-Version: 2.4
Name: ewoksid31
Version: 0.8.1
Summary: Data processing workflows for ID31
Author-email: ESRF <dau-pydev@esrf.fr>
Project-URL: Homepage, https://gitlab.esrf.fr/workflow/ewoksapps/ewoksid31/
Project-URL: Documentation, https://ewoksid31.readthedocs.io/
Project-URL: Repository, https://gitlab.esrf.fr/workflow/ewoks/ewoksapps/ewoksid31/
Project-URL: Issues, https://gitlab.esrf.fr/workflow/ewoksapps/ewoksid31/issues/
Project-URL: Changelog, https://gitlab.esrf.fr/workflow/ewoksapps/ewoksid31/-/blob/main/CHANGELOG.md
Keywords: ewoks
Classifier: Intended Audience :: Science/Research
Classifier: Programming Language :: Python :: 3
Requires-Python: >=3.10
License-File: LICENSE.md
Requires-Dist: ewokscore
Requires-Dist: ewoks>=0.1.2
Requires-Dist: ewoksjob[redis]>=1.0.0
Requires-Dist: ewoksorange
Requires-Dist: ewoksutils>=1.1.0
Requires-Dist: ewoksxrpd>=1.5.0
Requires-Dist: scipy
Requires-Dist: numpy
Requires-Dist: h5py
Requires-Dist: hdf5plugin
Requires-Dist: PyQt5
Requires-Dist: silx[full]
Requires-Dist: qtawesome
Requires-Dist: siphash24
Provides-Extra: test
Requires-Dist: pytest>=7; extra == "test"
Requires-Dist: pytest-qt; extra == "test"
Provides-Extra: dev
Requires-Dist: ewoksid31[test]; extra == "dev"
Requires-Dist: bandit; extra == "dev"
Requires-Dist: black>=25; extra == "dev"
Requires-Dist: flake8>=4; extra == "dev"
Requires-Dist: isort; extra == "dev"
Requires-Dist: mypy; extra == "dev"
Provides-Extra: doc
Requires-Dist: ewoksid31[dev]; extra == "doc"
Requires-Dist: ewokssphinx>=1.0.0; extra == "doc"
Requires-Dist: sphinx>=4.5; extra == "doc"
Requires-Dist: sphinx-autodoc-typehints>=1.16; extra == "doc"
Requires-Dist: pydata_sphinx_theme; extra == "doc"
Requires-Dist: sphinxcontrib-autoprogram; extra == "doc"
Requires-Dist: sphinx-argparse; extra == "doc"
Requires-Dist: sphinx-copybutton; extra == "doc"
Dynamic: license-file
